COPYRIGHT
MANIFEST.in
Makefile
README
setup.py
test/__init__.py
test/__init__.pyc
test/test_compile.py
test/test_compile.pyc
test/test_serialize.py
test/test_serialize.pyc
tiddlywebplugins/__init__.py
tiddlywebplugins.lazy.egg-info/PKG-INFO
tiddlywebplugins.lazy.egg-info/SOURCES.txt
tiddlywebplugins.lazy.egg-info/dependency_links.txt
tiddlywebplugins.lazy.egg-info/namespace_packages.txt
tiddlywebplugins.lazy.egg-info/not-zip-safe
tiddlywebplugins.lazy.egg-info/requires.txt
tiddlywebplugins.lazy.egg-info/top_level.txt
tiddlywebplugins/lazy/__init__.py
tiddlywebplugins/lazy/config.py
tiddlywebplugins/lazy/serialization.py