Metadata-Version: 1.0
Name: tiddlywebplugins.lazy
Version: 0.5
Summary: A TiddlyWeb plugin that makes tiddlywebwiki load lazy.
Home-page: UNKNOWN
Author: Chris Dent
Author-email: cdent@peermore.com
License: BSD
Platform: Posix; MacOS X; Windows
